gopass_utils/__init__.py
gopass_utils/gopass_utils.py
gopass_utils/gu_logger.py
gopass_utils/ssh_unlock.py
gopass_utils-0.5.0.dist-info/licenses/LICENSE
gopass_utils-0.5.0.dist-info/METADATA
gopass_utils-0.5.0.dist-info/WHEEL
gopass_utils-0.5.0.dist-info/entry_points.txt
gopass_utils-0.5.0.dist-info/top_level.txt
gopass_utils-0.5.0.dist-info/RECORD
