Metadata-Version: 2.4
Name: gopass_utils
Version: 0.5.0
Summary: Reusable Gopass interface for Python Projects
Author-email: Rick <ricks.homelab@gmail.com>
License-Expression: LicenseRef-Proprietary
Project-URL: homepage, https://github.com/Ricks-Lab/gopass-utils
Project-URL: documentation, https://github.com/Ricks-Lab/gopass-utils
Project-URL: source, https://github.com/Ricks-Lab/gopass-utils
Project-URL: bug-tracker, https://github.com/Ricks-Lab/gopass-utils/issues
Keywords: security,gpg,vault,password,gopass
Classifier: Development Status :: 4 - Beta
Classifier: Environment :: Console
Classifier: Intended Audience :: Developers
Classifier: Intended Audience :: End Users/Desktop
Classifier: Natural Language :: English
Classifier: Operating System :: POSIX
Classifier: Programming Language :: Python :: 3
Classifier: Programming Language :: Python :: 3.8
Classifier: Programming Language :: Python :: 3.9
Classifier: Programming Language :: Python :: 3.10
Classifier: Programming Language :: Python :: 3.11
Classifier: Programming Language :: Python :: 3.12
Classifier: Topic :: Security
Classifier: Topic :: Utilities
Classifier: Topic :: Software Development :: Libraries :: Python Modules
Requires-Python: >=3.8
License-File: LICENSE
Requires-Dist: pexpect>=4.9.0
Dynamic: license-file
